jamaisvu/__init__.py
jamaisvu/jamaisvu_argparse.py
jamaisvu/jamaisvu_csv.py
jamaisvu/jamaisvu_debug.py
jamaisvu/jamaisvu_json.py
jamaisvu/jamaisvu_math.py
jamaisvu/jamaisvu_omegaconf.py
jamaisvu/jamaisvu_pandas.py
jamaisvu/jamaisvu_path.py
jamaisvu/jamaisvu_progressbar.py
jamaisvu/jamaisvu_str.py
jamaisvu/jamaisvu_text.py
jamaisvu/jamaisvu_time.py
jamaisvu/jamaisvu_xlsx.py
jamaisvu/jamaisvu_yaml.py
jamaisvu-0.0.1.dist-info/LICENSE
jamaisvu-0.0.1.dist-info/METADATA
jamaisvu-0.0.1.dist-info/WHEEL
jamaisvu-0.0.1.dist-info/top_level.txt
jamaisvu-0.0.1.dist-info/RECORD
