Metadata-Version: 2.1
Name: jamaisvu
Version: 0.0.1
Home-page: https://github.com/vujadeyoon/jamaisvu-python
Author: vujadeyoon
Author-email: vujadeyoon@gmail.com
License: MIT License
Keywords: jamaisvu-python,jamaisvu
Classifier: Development Status :: 5 - Production/Stable
Classifier: Operating System :: OS Independent
Classifier: License :: OSI Approved :: MIT License
Classifier: Natural Language :: English
Classifier: Programming Language :: Python :: 3.7
Classifier: Programming Language :: Python :: 3.8
Classifier: Programming Language :: Python :: 3.9
Classifier: Programming Language :: Python :: 3.10
Classifier: Programming Language :: Python :: 3.11
Classifier: Programming Language :: Python :: 3.12
Classifier: Programming Language :: Python :: 3.13
Requires-Python: >=3.7
License-File: LICENSE
Requires-Dist: Cython
Requires-Dist: numpy
Requires-Dist: wheel
